picoter_simulator/__init__.py
picoter_simulator/button.py
picoter_simulator/button.pyi
picoter_simulator/display.py
picoter_simulator/display.pyi
picoter_simulator/picoter.py
picoter_simulator/picoter.pyi
picoter_simulator/py.typed
picoter_simulator-0.1.2.dist-info/LICENSE
picoter_simulator-0.1.2.dist-info/METADATA
picoter_simulator-0.1.2.dist-info/WHEEL
picoter_simulator-0.1.2.dist-info/RECORD
