Metadata-Version: 2.1
Name: picoter_simulator
Version: 0.1.2
Summary: The Simulator platform for picoter
Home-page: https://github.com/Letsric/picoter_simulator
License: MIT
Author: Letsric
Author-email: riccibrief@gmail.com
Requires-Python: >=3.10,<4.0
Classifier: License :: OSI Approved :: MIT License
Classifier: Programming Language :: Python :: 3
Classifier: Programming Language :: Python :: 3.10
Classifier: Programming Language :: Python :: 3.11
Classifier: Programming Language :: Python :: 3.12
Requires-Dist: mypy (>=1.8.0,<2.0.0)
Requires-Dist: numpy (>=1.26.3,<2.0.0)
Requires-Dist: pillow (>=10.2.0,<11.0.0)
Requires-Dist: pygame (>=2.5.2,<3.0.0)
Requires-Dist: pyright (>=1.1.348,<2.0.0)
Requires-Dist: thorpy (>=2.1.6,<3.0.0)
Project-URL: Repository, https://github.com/Letsric/picoter_simulator
